Metadata-Version: 2.0
Name: cs46-awesometrees
Version: 1.0.0
Summary: Include AVL, BST, HEAP, all those popular and must knowndata structures. From a CMC CS46 class:https://github.com/mikeizbicki/cmc-csci046
Home-page: https://github.com/StellaLX99/trees
Author: Stella Li
Author-email: stelli@students.pitzer.edu
License: GPL3
Platform: UNKNOWN
Classifier: License :: OSI Approved :: GNU General Public License v3 (GPLv3)
Classifier: Programming Language :: Python :: 3
Classifier: Programming Language :: Python :: 3.7
Requires-Dist: hypothesis
Requires-Dist: pytest
